bol/__init__.py
bol/openapi/__init__.py
bol/openapi/api.py
bol/retailer/__init__.py
bol/retailer/api.py
bol/retailer/models.py
python_bol_api_latest-1.4.0.dist-info/AUTHORS
python_bol_api_latest-1.4.0.dist-info/LICENSE
python_bol_api_latest-1.4.0.dist-info/METADATA
python_bol_api_latest-1.4.0.dist-info/WHEEL
python_bol_api_latest-1.4.0.dist-info/top_level.txt
python_bol_api_latest-1.4.0.dist-info/RECORD
