Metadata-Version: 2.1
Name: python-bol-api-latest
Version: 1.4.0
Summary: Wrapper for the bol.com API
Home-page: https://dreambits.in
Author: Raymond Penners, Dreambits Technologies Pvt. Ltd.
Author-email: office@dreambits.in
Keywords: bol bol.com api wrapper
Classifier: Development Status :: 5 - Production/Stable
Classifier: Intended Audience :: Developers
Classifier: Intended Audience :: System Administrators
Classifier: Operating System :: OS Independent
Classifier: Topic :: Software Development
Classifier: Topic :: System
Classifier: Topic :: System :: Software Distribution
Classifier: Programming Language :: Python :: 2
Classifier: Programming Language :: Python :: 2.7
Classifier: Programming Language :: Python :: 3
Classifier: Programming Language :: Python :: 3.8
Classifier: License :: OSI Approved :: GNU Lesser General Public License v3 or later (LGPLv3+)
License-File: LICENSE
License-File: AUTHORS
Requires-Dist: python-dateutil
Requires-Dist: requests
